hello_baby/__init__.py
hello_baby/__main__.py
hello_baby/get_quote.py
hello_baby/main.py
hello_baby/quotes.py
hello_baby-4.0.0.dist-info/LICENSE
hello_baby-4.0.0.dist-info/METADATA
hello_baby-4.0.0.dist-info/WHEEL
hello_baby-4.0.0.dist-info/entry_points.txt
hello_baby-4.0.0.dist-info/RECORD
