Metadata-Version: 2.1
Name: hello-baby
Version: 4.0.0
Summary: 
Author: younthing
Author-email: fanxingfu3344@gmail.com
Requires-Python: >=3.11,<4.0
Classifier: Programming Language :: Python :: 3
Classifier: Programming Language :: Python :: 3.11
Classifier: Programming Language :: Python :: 3.12
Requires-Dist: sphinx (>=7.4.7,<8.0.0)
Requires-Dist: sphinx-book-theme (>=1.1.3,<2.0.0)
